factly/__init__.py
factly/__main__.py
factly/benchmarks.py
factly/cli.py
factly/models.py
factly/plots.py
factly/resources.py
factly/tasks.py
factly_eval-1.0.1.dist-info/METADATA
factly_eval-1.0.1.dist-info/WHEEL
factly_eval-1.0.1.dist-info/entry_points.txt
factly_eval-1.0.1.dist-info/licenses/LICENSE
factly_eval-1.0.1.dist-info/RECORD
