Metadata-Version: 2.4
Name: factly-eval
Version: 1.0.1
Summary: CLI tool to evaluate ChatGPT factuality on MMLU benchmark.
Project-URL: Homepage, https://factly.readthedocs.io
Project-URL: Repository, https://github.com/sergeyklay/factly
Project-URL: Documentation, https://factly.readthedocs.io/en/latest/index.html
Project-URL: Changelog, https://factly.readthedocs.io/en/latest/changelog.html
Project-URL: Issues, https://github.com/sergeyklay/factly/issues
Project-URL: Download, https://github.com/sergeyklay/factly/releases
Author-email: Serghei Iakovlev <oss@serghei.pl>
License-Expression: MIT
License-File: LICENSE
Keywords: ai-evaluation,benchmark,chatgpt,cli,evaluation,factuality,llm,mmlu,openai,prompt-engineering
Classifier: Development Status :: 4 - Beta
Classifier: Environment :: Console
Classifier: Intended Audience :: Developers
Classifier: Intended Audience :: Science/Research
Classifier: Operating System :: OS Independent
Classifier: Programming Language :: Python :: 3
Classifier: Programming Language :: Python :: 3.12
Classifier: Programming Language :: Python :: 3.13
Classifier: Programming Language :: Python :: Implementation :: CPython
Classifier: Topic :: Scientific/Engineering
Classifier: Topic :: Scientific/Engineering :: Artificial Intelligence
Classifier: Topic :: Scientific/Engineering :: Information Analysis
Classifier: Topic :: Software Development :: Libraries :: Python Modules
Classifier: Topic :: Software Development :: Testing
Classifier: Topic :: Utilities
Classifier: Typing :: Typed
Requires-Python: <4,>=3.12
Requires-Dist: click
Requires-Dist: datasets>=3.5.1
Requires-Dist: deepeval<3.0.0,>=2.8.1
Requires-Dist: matplotlib>=3.10.1
Requires-Dist: pandas>=2.2.3
Requires-Dist: psutil>=7.0.0
Requires-Dist: python-dotenv>=1.1.0
Requires-Dist: pyyaml>=6.0.2
Requires-Dist: transformers>=4.51.3
